napalm_netgear/__init__.py
napalm_netgear/netgear.py
napalm_netgear/parser.py
napalm_netgear-0.0.2.dist-info/LICENSE
napalm_netgear-0.0.2.dist-info/METADATA
napalm_netgear-0.0.2.dist-info/WHEEL
napalm_netgear-0.0.2.dist-info/top_level.txt
napalm_netgear-0.0.2.dist-info/RECORD
