Metadata-Version: 2.1
Name: napalm_netgear
Version: 0.0.2
Summary: NAPALM module for Netgear switches
Author-email: shrank <info@murxs.ch>
License: This is free and unencumbered software released into the public domain.
Project-URL: Homepage, https://github.com/shrank/napalm_netgear
Keywords: network,automation,netgear
Classifier: Programming Language :: Python :: 3
Classifier: Operating System :: OS Independent
Requires-Python: >=3.0
License-File: LICENSE
Requires-Dist: napalm
